{"demo":{"category":"vue","type":"1","block":0,"pages":[{"template":"28/demo.vue","type":"page","fileName":"demo","poster":".vue"}]},"miniBasic":{"category":"miniapp","type":"1","block":0,"pages":[{"template":"31/index.js","type":"page","fileName":"index","poster":".js"},{"template":"31/index.json","type":"page","fileName":"index","poster":".json"},{"template":"31/index.wxml","type":"page","fileName":"index","poster":".wxml"},{"template":"31/index.wxss","type":"page","fileName":"index","poster":".wxss"}]},"miniEdit":{"category":"miniapp","type":"1","block":0,"pages":[{"template":"32/index.wxml","type":"page","fileName":"index","poster":".wxml"},{"template":"32/index.js","type":"page","fileName":"index","poster":".js"},{"template":"32/index.json","type":"page","fileName":"index","poster":".json"},{"template":"32/index.wxss","type":"page","fileName":"index","poster":".wxss"}]},"miniList":{"category":"miniapp","type":"1","block":0,"pages":[{"template":"33/index.js","type":"page","fileName":"index","poster":".js"},{"template":"33/index.json","type":"page","fileName":"index","poster":".json"},{"template":"33/index.wxml","type":"page","fileName":"index","poster":".wxml"},{"template":"33/index.wxss","type":"page","fileName":"index","poster":".wxss"}]},"workAudd":{"category":"vue","type":"1","block":0,"pages":[{"template":"29/list.vue","type":"page","fileName":"list","poster":".vue"},{"template":"29/detail.vue","type":"page","fileName":"detail","poster":".vue"}]},"zlAudd":{"category":"vue","type":"1","block":0,"pages":[{"template":"30/api.js","type":"api","fileName":"api","poster":".js"},{"template":"30/detail.vue","type":"page","fileName":"detail","poster":".vue"},{"template":"30/list.vue","type":"page","fileName":"list","poster":".vue"},{"template":"30/store.js","type":"store","fileName":"store","poster":".js"}]}}